LICENSE
README.md
setup.cfg
setup.py
src/pydocmaker/__init__.py
src/pydocmaker/core.py
src/pydocmaker/templating.py
src/pydocmaker/util.py
src/pydocmaker.egg-info/PKG-INFO
src/pydocmaker.egg-info/SOURCES.txt
src/pydocmaker.egg-info/dependency_links.txt
src/pydocmaker.egg-info/requires.txt
src/pydocmaker.egg-info/top_level.txt
src/pydocmaker/backend/__init__.py
src/pydocmaker/backend/baseformatter.py
src/pydocmaker/backend/ex_docx.py
src/pydocmaker/backend/ex_html.py
src/pydocmaker/backend/ex_ipynb.py
src/pydocmaker/backend/ex_markdown.py
src/pydocmaker/backend/ex_redmine.py
src/pydocmaker/backend/ex_tex.py
src/pydocmaker/backend/mdx_latex.py
src/pydocmaker/backend/pandoc_api.py
src/pydocmaker/backend/pdf_maker.py
tests/test_backend_pandoc.py
tests/test_convert_all.py
tests/test_core.py
tests/test_docx_ex.py
tests/test_ex_html.py
tests/test_util.py