Metadata-Version: 2.1
Name: pydocmaker
Version: 2.4.0
Summary: a minimal document maker to make docx, markdown, html, textile, redmine, and tex documents from python. Written in pure python.
Home-page: https://github.com/TobiasGlaubach/pydocmaker
Author: Tobias Glaubach
Project-URL: Bug Tracker, https://github.com/TobiasGlaubach/pydocmaker/issues
Classifier: Operating System :: OS Independent
Classifier: Programming Language :: Python
Classifier: Programming Language :: Python :: 3
Classifier: Programming Language :: Python :: 3 :: Only
Requires-Python: >=3.8
License-File: LICENSE
Requires-Dist: markdown
Requires-Dist: python-docx
Requires-Dist: requests
Requires-Dist: latex
Requires-Dist: jinja2
Requires-Dist: docxcompose
Requires-Dist: docx-mailmerge
